reloci/__init__.py
reloci/check_interval.py
reloci/cli.py
reloci/file_info.py
reloci/planner.py
reloci/py.typed
reloci/renamer.py
reloci/worker.py
reloci-7.0.dist-info/licenses/LICENSE
reloci-7.0.dist-info/WHEEL
reloci-7.0.dist-info/entry_points.txt
reloci-7.0.dist-info/METADATA
reloci-7.0.dist-info/RECORD
