Metadata-Version: 2.4
Name: reloci
Version: 7.0
Summary: Organize photos based on exif
Keywords: photos,exif,date,directories,organize
Author: Arne de Laat
Author-email: Arne de Laat <arne@delaat.net>
License-Expression: MIT
License-File: LICENSE
Classifier: License :: OSI Approved :: MIT License
Classifier: Programming Language :: Python
Classifier: Programming Language :: Python :: 3
Classifier: Topic :: Desktop Environment :: File Managers
Requires-Dist: pyexiftool==0.5.6
Requires-Dist: python-baseconv==1.2.2
Requires-Dist: rich==14.2.0
Requires-Dist: coverage==7.10.7 ; extra == 'dev'
Requires-Dist: ty==0.0.1a22 ; extra == 'dev'
Maintainer: Arne de Laat
Maintainer-email: Arne de Laat <arne@delaat.net>
Requires-Python: >=3.13
Project-URL: Repository, https://github.com/153957/reloci/
Provides-Extra: dev
